{"category":"validation","description":"Draft-verify-revise — reduces hallucination via independent fact-checking","input_shape":{"fields":[{"doc":"Number of verification questions (default: 3)","name":"n_questions","optional":true,"type":{"kind":"primitive","name":"number"}},{"doc":"The question/task to answer","name":"task","optional":false,"type":{"kind":"primitive","name":"string"}}],"open":true},"name":"cove","narrative_md":"---\nname: cove\nversion: 0.1.0\ncategory: validation\nresult_shape: \"shape { draft: string, final_response: string, verifications: array of shape { answer: string, question: string } }\"\ndescription: \"Draft-verify-revise — reduces hallucination via independent fact-checking\"\nsource: cove/init.lua\ngenerated: gen_docs (V0)\n---\n\n# CoVe — Chain-of-Verification: draft-verify-revise cycle\n\n> Reduces hallucination by: draft → generate verification questions → answer them independently → produce verified final response.\n\n## Contents\n\n- [Parameters](#parameters)\n- [Result](#result)\n\n## Parameters {#parameters}\n\n| key | type | required | description |\n|---|---|---|---|\n| `ctx.n_questions` | number | optional | Number of verification questions (default: 3) |\n| `ctx.task` | string | **required** | The question/task to answer |\n\n## Result {#result}\n\nReturns:\n\n| key | type | optional | description |\n|---|---|---|---|\n| `draft` | string | — | Baseline draft answer |\n| `final_response` | string | — | Final answer after fact-check revision |\n| `verifications` | array of shape { answer: string, question: string } | — | Per-question verification records (may be shorter than n_questions) |\n","result_shape":{"kind":"shape","shape":{"fields":[{"doc":"Baseline draft answer","name":"draft","optional":false,"type":{"kind":"primitive","name":"string"}},{"doc":"Final answer after fact-check revision","name":"final_response","optional":false,"type":{"kind":"primitive","name":"string"}},{"doc":"Per-question verification records (may be shorter than n_questions)","name":"verifications","optional":false,"type":{"kind":"array_of","of":{"kind":"shape","shape":{"fields":[{"doc":"Independent answer to the verification question","name":"answer","optional":false,"type":{"kind":"primitive","name":"string"}},{"doc":"Verification question text","name":"question","optional":false,"type":{"kind":"primitive","name":"string"}}],"open":true}}}}],"open":true}},"version":"0.1.0"}