{"category":"combinator","description":"Feasibility-gated proposal filtering — prerequisite verification before rating","name":"pre_mortem","narrative_md":"---\nname: pre_mortem\nversion: 0.1.0\ncategory: combinator\ndescription: \"Feasibility-gated proposal filtering — prerequisite verification before rating\"\nsource: pre_mortem/init.lua\ngenerated: gen_docs (V0)\n---\n\n# pre_mortem — feasibility-gated proposal filtering\n\n> Combinator package: orchestrates factscore, contrastive, calibrate to validate proposals BEFORE output. Decomposes each proposal into prerequisite assumptions, checks verification status, generates rejection reasons pre-emptively, and demotes/filters proposals with unverified prerequisites.\n","version":"0.1.0"}